{
  "name": "Unnamed region 04",
  "cities": [
    {
      "cityName": "Albrechtice",
      "lat": 50.75,
      "lng": 15.3
    },
    {
      "cityName": "Alsovice",
      "lat": 50.6833333,
      "lng": 15.2333333
    },
    {
      "cityName": "Bedrichov",
      "lat": 50.7166667,
      "lng": 15.6
    },
    {
      "cityName": "Besedice",
      "lat": 50.6333333,
      "lng": 15.2166667
    },
    {
      "cityName": "Bohdalovice",
      "lat": 50.7166667,
      "lng": 15.3166667
    },
    {
      "cityName": "Bohunovsko",
      "lat": 50.65,
      "lng": 15.3166667
    },
    {
      "cityName": "Boskow",
      "lat": 50.6336111,
      "lng": 15.3377778
    },
    {
      "cityName": "Bratrikov",
      "lat": 50.6833333,
      "lng": 15.25
    },
    {
      "cityName": "Bratrouchov",
      "lat": 50.7,
      "lng": 15.4666667
    },
    {
      "cityName": "Burany",
      "lat": 50.7,
      "lng": 15.45
    },
    {
      "cityName": "Bzí",
      "lat": 50.6666667,
      "lng": 15.2166667
    },
    {
      "cityName": "Cerna Ricka",
      "lat": 50.7833333,
      "lng": 15.3333333
    },
    {
      "cityName": "Chlístov",
      "lat": 50.65,
      "lng": 15.2333333
    },
    {
      "cityName": "Cista Voda",
      "lat": 50.6833333,
      "lng": 15.5666667
    },
    {
      "cityName": "Desná",
      "lat": 50.7588889,
      "lng": 15.3136111
    },
    {
      "cityName": "Dlouhý",
      "lat": 50.6166667,
      "lng": 15.25
    },
    {
      "cityName": "Dolni Dusnice",
      "lat": 50.6833333,
      "lng": 15.45
    },
    {
      "cityName": "Dolní Polubný",
      "lat": 50.7666667,
      "lng": 15.35
    },
    {
      "cityName": "Drzkov",
      "lat": 50.7,
      "lng": 15.3166667
    },
    {
      "cityName": "Eisenbrod",
      "lat": 50.6411111,
      "lng": 15.2522222
    },
    {
      "cityName": "Georgenthal",
      "lat": 50.75,
      "lng": 15.2666667
    },
    {
      "cityName": "Háje",
      "lat": 50.6166667,
      "lng": 15.4166667
    },
    {
      "cityName": "Haratice",
      "lat": 50.7,
      "lng": 15.3333333
    },
    {
      "cityName": "Harrachov",
      "lat": 50.77,
      "lng": 15.4247222
    },
    {
      "cityName": "Havírna",
      "lat": 50.7333333,
      "lng": 15.4
    },
    {
      "cityName": "Helkovice",
      "lat": 50.65,
      "lng": 15.3833333
    },
    {
      "cityName": "Hochstadt",
      "lat": 50.6833333,
      "lng": 15.4
    },
    {
      "cityName": "Horni Cerna Studnice",
      "lat": 50.7166667,
      "lng": 15.2166667
    },
    {
      "cityName": "Horská Kamenice",
      "lat": 50.65,
      "lng": 15.3
    },
    {
      "cityName": "Hrubá Horka",
      "lat": 50.65,
      "lng": 15.2666667
    },
    {
      "cityName": "Hut",
      "lat": 50.7,
      "lng": 15.2333333
    },
    {
      "cityName": "Jablonec an der Iser",
      "lat": 50.6994444,
      "lng": 15.4241667
    },
    {
      "cityName": "Jeseney",
      "lat": 50.65,
      "lng": 15.35
    },
    {
      "cityName": "Jilove u Drzkova",
      "lat": 50.6666667,
      "lng": 15.2833333
    },
    {
      "cityName": "Jirkov",
      "lat": 50.6666667,
      "lng": 15.2666667
    },
    {
      "cityName": "Jizerka",
      "lat": 50.8166667,
      "lng": 15.35
    },
    {
      "cityName": "Koberovy",
      "lat": 50.6166667,
      "lng": 15.2166667
    },
    {
      "cityName": "Korenov",
      "lat": 50.7680556,
      "lng": 15.3638889
    },
    {
      "cityName": "Krausebauden",
      "lat": 50.7166667,
      "lng": 15.5833333
    },
    {
      "cityName": "Labská Bouda",
      "lat": 50.7666667,
      "lng": 15.55
    },
    {
      "cityName": "Lisny",
      "lat": 50.65,
      "lng": 15.2166667
    },
    {
      "cityName": "Loukov",
      "lat": 50.6166667,
      "lng": 15.4
    },
    {
      "cityName": "Louznice",
      "lat": 50.6833333,
      "lng": 15.2666667
    },
    {
      "cityName": "Lucany",
      "lat": 50.7333333,
      "lng": 15.2166667
    },
    {
      "cityName": "Malá Horka",
      "lat": 50.65,
      "lng": 15.2833333
    },
    {
      "cityName": "Mariánská Hora",
      "lat": 50.7666667,
      "lng": 15.2833333
    },
    {
      "cityName": "Michovka",
      "lat": 50.6166667,
      "lng": 15.2
    },
    {
      "cityName": "Morchenstern",
      "lat": 50.7369444,
      "lng": 15.2358333
    },
    {
      "cityName": "Návarov",
      "lat": 50.6833333,
      "lng": 15.3166667
    },
    {
      "cityName": "Neuwelt",
      "lat": 50.7833333,
      "lng": 15.4166667
    },
    {
      "cityName": "Ober Hammer",
      "lat": 50.7194444,
      "lng": 15.3161111
    },
    {
      "cityName": "Ochsengraben",
      "lat": 50.6833333,
      "lng": 15.5833333
    },
    {
      "cityName": "Paseky nad Jizerou",
      "lat": 50.7166667,
      "lng": 15.4
    },
    {
      "cityName": "Pelechov",
      "lat": 50.6333333,
      "lng": 15.2833333
    },
    {
      "cityName": "Pipice",
      "lat": 50.6166667,
      "lng": 15.2666667
    },
    {
      "cityName": "Podspalov",
      "lat": 50.6333333,
      "lng": 15.3166667
    },
    {
      "cityName": "Polaun",
      "lat": 50.7666667,
      "lng": 15.3333333
    },
    {
      "cityName": "Prackov",
      "lat": 50.6,
      "lng": 15.25
    },
    {
      "cityName": "Prichovice",
      "lat": 50.75,
      "lng": 15.35
    },
    {
      "cityName": "Prikry",
      "lat": 50.6166667,
      "lng": 15.3666667
    },
    {
      "cityName": "Pustiny",
      "lat": 50.75,
      "lng": 15.3333333
    },
    {
      "cityName": "Rejdice",
      "lat": 50.7166667,
      "lng": 15.3666667
    },
    {
      "cityName": "Roztoky",
      "lat": 50.6666667,
      "lng": 15.3666667
    },
    {
      "cityName": "Schenkenhahn",
      "lat": 50.75,
      "lng": 15.3666667
    },
    {
      "cityName": "Schumburg",
      "lat": 50.75,
      "lng": 15.3166667
    },
    {
      "cityName": "Skelne Hute",
      "lat": 50.7166667,
      "lng": 15.5333333
    },
    {
      "cityName": "Sklenarice",
      "lat": 50.7,
      "lng": 15.3833333
    },
    {
      "cityName": "Slap",
      "lat": 50.6166667,
      "lng": 15.2833333
    },
    {
      "cityName": "Smrci",
      "lat": 50.6,
      "lng": 15.2333333
    },
    {
      "cityName": "Spindelmühle",
      "lat": 50.7236111,
      "lng": 15.5994444
    },
    {
      "cityName": "Stanový",
      "lat": 50.6833333,
      "lng": 15.35
    },
    {
      "cityName": "Stará Ves",
      "lat": 50.6833333,
      "lng": 15.3833333
    },
    {
      "cityName": "Svárov",
      "lat": 50.7411111,
      "lng": 15.3238889
    },
    {
      "cityName": "Svatý Petr",
      "lat": 50.7166667,
      "lng": 15.6333333
    },
    {
      "cityName": "Tannwald",
      "lat": 50.7408333,
      "lng": 15.2677778
    },
    {
      "cityName": "Tric",
      "lat": 50.6833333,
      "lng": 15.4333333
    },
    {
      "cityName": "Václavíkova Studánka",
      "lat": 50.7833333,
      "lng": 15.35
    },
    {
      "cityName": "Vítkovice",
      "lat": 50.6833333,
      "lng": 15.5333333
    },
    {
      "cityName": "Vlastibor",
      "lat": 50.6666667,
      "lng": 15.3166667
    },
    {
      "cityName": "Vrát",
      "lat": 50.6333333,
      "lng": 15.2333333
    },
    {
      "cityName": "Zabyly",
      "lat": 50.75,
      "lng": 15.4166667
    },
    {
      "cityName": "Zásada",
      "lat": 50.7,
      "lng": 15.2666667
    },
    {
      "cityName": "Zlata Olesnice-Semilska",
      "lat": 50.7166667,
      "lng": 15.35
    }
  ]
}