{
  "name": "Unnamed region 10",
  "cities": [
    {
      "cityName": "Andreevca",
      "lat": 47.5388889,
      "lng": 28.8775
    },
    {
      "cityName": "Bachushka",
      "lat": 47.6388889,
      "lng": 28.9869444
    },
    {
      "cityName": "Bagu",
      "lat": 47.4225,
      "lng": 28.4666667
    },
    {
      "cityName": "Berezlodzh'",
      "lat": 47.4363889,
      "lng": 28.9338889
    },
    {
      "cityName": "Bezen",
      "lat": 47.2844444,
      "lng": 28.67
    },
    {
      "cityName": "Biesti",
      "lat": 47.5155556,
      "lng": 28.8613889
    },
    {
      "cityName": "Bogzesht'",
      "lat": 47.4247222,
      "lng": 28.4283333
    },
    {
      "cityName": "Bologan'",
      "lat": 47.4319444,
      "lng": 28.8730556
    },
    {
      "cityName": "Botushany",
      "lat": 47.5336111,
      "lng": 29.0258333
    },
    {
      "cityName": "Braneshty",
      "lat": 47.3052778,
      "lng": 28.9266667
    },
    {
      "cityName": "Bravicea",
      "lat": 47.3611111,
      "lng": 28.4361111
    },
    {
      "cityName": "Braviceni",
      "lat": 47.4336111,
      "lng": 28.6577778
    },
    {
      "cityName": "Breanova",
      "lat": 47.4158333,
      "lng": 28.6497222
    },
    {
      "cityName": "Budai",
      "lat": 47.4344444,
      "lng": 28.8211111
    },
    {
      "cityName": "Bulaesti",
      "lat": 47.4769444,
      "lng": 28.9786111
    },
    {
      "cityName": "Busauca",
      "lat": 47.5936111,
      "lng": 28.7886111
    },
    {
      "cityName": "Butuceni",
      "lat": 47.3013889,
      "lng": 28.9725
    },
    {
      "cityName": "Camencea",
      "lat": 47.2808333,
      "lng": 28.6875
    },
    {
      "cityName": "Chegoren'",
      "lat": 47.5061111,
      "lng": 28.8622222
    },
    {
      "cityName": "Chekolteny",
      "lat": 47.4938889,
      "lng": 28.6088889
    },
    {
      "cityName": "Chersac",
      "lat": 47.6375,
      "lng": 28.5841667
    },
    {
      "cityName": "Chinisheuts'",
      "lat": 47.6955556,
      "lng": 28.855
    },
    {
      "cityName": "Chiperceni",
      "lat": 47.525,
      "lng": 28.8386111
    },
    {
      "cityName": "Chishma",
      "lat": 47.4163889,
      "lng": 28.7533333
    },
    {
      "cityName": "Chistelnita",
      "lat": 47.5680556,
      "lng": 28.6608333
    },
    {
      "cityName": "Chitcanii Noi",
      "lat": 47.5652778,
      "lng": 28.4819444
    },
    {
      "cityName": "Chitcanii Vechi",
      "lat": 47.5927778,
      "lng": 28.5011111
    },
    {
      "cityName": "Clisova",
      "lat": 47.4730556,
      "lng": 28.5736111
    },
    {
      "cityName": "Cobâlca",
      "lat": 47.2866667,
      "lng": 28.5897222
    },
    {
      "cityName": "Codrul Nou",
      "lat": 47.5477778,
      "lng": 28.5772222
    },
    {
      "cityName": "Cogâlniceni",
      "lat": 47.6347222,
      "lng": 28.8225
    },
    {
      "cityName": "Coropceni",
      "lat": 47.4761111,
      "lng": 28.5222222
    },
    {
      "cityName": "Cotovscoe",
      "lat": 47.5227778,
      "lng": 28.7211111
    },
    {
      "cityName": "Crasnaseni",
      "lat": 47.4333333,
      "lng": 28.3988889
    },
    {
      "cityName": "Cucuruzeni",
      "lat": 47.4883333,
      "lng": 28.7258333
    },
    {
      "cityName": "Cucuruzenii de Sus",
      "lat": 47.5455556,
      "lng": 28.6988889
    },
    {
      "cityName": "Cuizauca",
      "lat": 47.6144444,
      "lng": 28.8127778
    },
    {
      "cityName": "Curchi",
      "lat": 47.3358333,
      "lng": 28.6538889
    },
    {
      "cityName": "Dascova",
      "lat": 47.3755556,
      "lng": 28.5975
    },
    {
      "cityName": "Dobrusa",
      "lat": 47.6144444,
      "lng": 28.5566667
    },
    {
      "cityName": "Domniy",
      "lat": 47.3558333,
      "lng": 28.8155556
    },
    {
      "cityName": "Echimauti",
      "lat": 47.6941667,
      "lng": 28.9002778
    },
    {
      "cityName": "Fedoreuca",
      "lat": 47.4880556,
      "lng": 28.6402778
    },
    {
      "cityName": "Furceni",
      "lat": 47.3363889,
      "lng": 28.9255556
    },
    {
      "cityName": "Fuzauca",
      "lat": 47.7416667,
      "lng": 28.7461111
    },
    {
      "cityName": "Germanesht'",
      "lat": 47.4402778,
      "lng": 28.5172222
    },
    {
      "cityName": "Gertop-Mik",
      "lat": 47.2469444,
      "lng": 28.9283333
    },
    {
      "cityName": "Getlova",
      "lat": 47.3719444,
      "lng": 28.5322222
    },
    {
      "cityName": "Ghiduleni",
      "lat": 47.6108333,
      "lng": 28.7447222
    },
    {
      "cityName": "Gizhdiyany",
      "lat": 47.4594444,
      "lng": 28.9147222
    },
    {
      "cityName": "Gluboaka",
      "lat": 47.3786111,
      "lng": 28.555
    },
    {
      "cityName": "Gordinesht'",
      "lat": 47.6966667,
      "lng": 28.8011111
    },
    {
      "cityName": "Gorodishche",
      "lat": 47.6147222,
      "lng": 28.9430556
    },
    {
      "cityName": "Greblesht'",
      "lat": 47.2397222,
      "lng": 28.6127778
    },
    {
      "cityName": "Ignatei",
      "lat": 47.6825,
      "lng": 28.6616667
    },
    {
      "cityName": "Inculet",
      "lat": 47.4488889,
      "lng": 28.7219444
    },
    {
      "cityName": "Indarapnici",
      "lat": 47.5936111,
      "lng": 28.5833333
    },
    {
      "cityName": "Isacova",
      "lat": 47.3702778,
      "lng": 28.7180556
    },
    {
      "cityName": "Ishnovets",
      "lat": 47.2313889,
      "lng": 28.8636111
    },
    {
      "cityName": "Isvoare",
      "lat": 47.5516667,
      "lng": 28.9572222
    },
    {
      "cityName": "Ivancea",
      "lat": 47.2847222,
      "lng": 28.8569444
    },
    {
      "cityName": "Jeloboc",
      "lat": 47.3569444,
      "lng": 28.9047222
    },
    {
      "cityName": "Jora de Mijloc",
      "lat": 47.4755556,
      "lng": 29.0961111
    },
    {
      "cityName": "Jora de Sus",
      "lat": 47.4866667,
      "lng": 29.0761111
    },
    {
      "cityName": "Jura",
      "lat": 47.5177778,
      "lng": 29.0430556
    },
    {
      "cityName": "Khodorozha",
      "lat": 47.5083333,
      "lng": 28.8886111
    },
    {
      "cityName": "Kurleny",
      "lat": 47.5594444,
      "lng": 28.7825
    },
    {
      "cityName": "Lalova",
      "lat": 47.5638889,
      "lng": 29.0191667
    },
    {
      "cityName": "Lapatna",
      "lat": 47.495,
      "lng": 29.0522222
    },
    {
      "cityName": "Lazo",
      "lat": 47.3666667,
      "lng": 28.8941667
    },
    {
      "cityName": "Leuseni",
      "lat": 47.4827778,
      "lng": 28.4352778
    },
    {
      "cityName": "Lucaseuca",
      "lat": 47.335,
      "lng": 28.7558333
    },
    {
      "cityName": "Luceafar",
      "lat": 47.4111111,
      "lng": 28.7786111
    },
    {
      "cityName": "Lupa-Recea",
      "lat": 47.3127778,
      "lng": 28.5925
    },
    {
      "cityName": "Malaesti",
      "lat": 47.4630556,
      "lng": 28.6636111
    },
    {
      "cityName": "Mana",
      "lat": 47.3388889,
      "lng": 28.6844444
    },
    {
      "cityName": "Martinesht'",
      "lat": 47.2352778,
      "lng": 28.6069444
    },
    {
      "cityName": "Mârzaci",
      "lat": 47.4894444,
      "lng": 28.9947222
    },
    {
      "cityName": "Marzesti",
      "lat": 47.4986111,
      "lng": 28.995
    },
    {
      "cityName": "Meseni",
      "lat": 47.6647222,
      "lng": 28.6380556
    },
    {
      "cityName": "Miclesti",
      "lat": 47.2386111,
      "lng": 28.8066667
    },
    {
      "cityName": "Mincenii de Jos",
      "lat": 47.6358333,
      "lng": 28.8758333
    },
    {
      "cityName": "Mincenii de Sus",
      "lat": 47.6494444,
      "lng": 28.8938889
    },
    {
      "cityName": "Mîndra",
      "lat": 47.535,
      "lng": 28.5261111
    },
    {
      "cityName": "Mitoc",
      "lat": 47.3866667,
      "lng": 28.785
    },
    {
      "cityName": "Mitocul Nou",
      "lat": 47.4033333,
      "lng": 28.7741667
    },
    {
      "cityName": "Morozeni Mari",
      "lat": 47.3780556,
      "lng": 28.6341667
    },
    {
      "cityName": "Neculaieuca",
      "lat": 47.3602778,
      "lng": 28.6922222
    },
    {
      "cityName": "Negureni",
      "lat": 47.6016667,
      "lng": 28.5111111
    },
    {
      "cityName": "Nistreni",
      "lat": 47.5411111,
      "lng": 29.01
    },
    {
      "cityName": "Noroceni",
      "lat": 47.3769444,
      "lng": 28.5180556
    },
    {
      "cityName": "Novaya Sakharna",
      "lat": 47.6758333,
      "lng": 28.9561111
    },
    {
      "cityName": "Novyye Sarateny",
      "lat": 47.5091667,
      "lng": 28.5013889
    },
    {
      "cityName": "Ocnita-Razesi",
      "lat": 47.4694444,
      "lng": 28.7202778
    },
    {
      "cityName": "Ocnita-Tarani",
      "lat": 47.4572222,
      "lng": 28.7227778
    },
    {
      "cityName": "Ofatinti",
      "lat": 47.6688889,
      "lng": 28.9961111
    },
    {
      "cityName": "Oneshti",
      "lat": 47.2786111,
      "lng": 28.5511111
    },
    {
      "cityName": "Orgeyev",
      "lat": 47.3830556,
      "lng": 28.8230556
    },
    {
      "cityName": "Otac",
      "lat": 47.5894444,
      "lng": 28.8297222
    },
    {
      "cityName": "Paharniceni",
      "lat": 47.3736111,
      "lng": 28.8844444
    },
    {
      "cityName": "Pecestea",
      "lat": 47.7155556,
      "lng": 28.7108333
    },
    {
      "cityName": "Pereni",
      "lat": 47.6555556,
      "lng": 28.7766667
    },
    {
      "cityName": "Peresechika",
      "lat": 47.2522222,
      "lng": 28.7688889
    },
    {
      "cityName": "Pocsesti",
      "lat": 47.2491667,
      "lng": 28.6833333
    },
    {
      "cityName": "Pogrebeni",
      "lat": 47.5563889,
      "lng": 28.9091667
    },
    {
      "cityName": "Popenchi",
      "lat": 47.5958333,
      "lng": 29.0136111
    },
    {
      "cityName": "Pripiceni-Curchi",
      "lat": 47.6827778,
      "lng": 28.7836111
    },
    {
      "cityName": "Pripiceni-Razesi",
      "lat": 47.6858333,
      "lng": 28.7630556
    },
    {
      "cityName": "Putintei",
      "lat": 47.3738889,
      "lng": 28.5761111
    },
    {
      "cityName": "Rascova",
      "lat": 47.2525,
      "lng": 28.8461111
    },
    {
      "cityName": "Ratush",
      "lat": 47.5369444,
      "lng": 28.5033333
    },
    {
      "cityName": "Romaneshty",
      "lat": 47.2258333,
      "lng": 28.7111111
    },
    {
      "cityName": "Roscanii de Jos",
      "lat": 47.6466667,
      "lng": 28.7375
    },
    {
      "cityName": "Roscanii de Sus",
      "lat": 47.6288889,
      "lng": 28.7688889
    },
    {
      "cityName": "Roscani",
      "lat": 47.6538889,
      "lng": 28.7408333
    },
    {
      "cityName": "Saharna",
      "lat": 47.6936111,
      "lng": 28.9702778
    },
    {
      "cityName": "Samananca",
      "lat": 47.265,
      "lng": 28.7308333
    },
    {
      "cityName": "Saratenii Vechi",
      "lat": 47.5261111,
      "lng": 28.5530556
    },
    {
      "cityName": "Sarcani",
      "lat": 47.5119444,
      "lng": 28.9322222
    },
    {
      "cityName": "Sârcova",
      "lat": 47.7413889,
      "lng": 28.7836111
    },
    {
      "cityName": "Saseni",
      "lat": 47.3677778,
      "lng": 28.5013889
    },
    {
      "cityName": "Scorteni",
      "lat": 47.6413889,
      "lng": 28.6463889
    },
    {
      "cityName": "Selishte",
      "lat": 47.3333333,
      "lng": 28.7844444
    },
    {
      "cityName": "Sirota",
      "lat": 47.5277778,
      "lng": 28.7769444
    },
    {
      "cityName": "Sloboda-Gorodishte",
      "lat": 47.5983333,
      "lng": 28.9355556
    },
    {
      "cityName": "Step'-Soch'",
      "lat": 47.4552778,
      "lng": 28.7897222
    },
    {
      "cityName": "Stetcani",
      "lat": 47.2363889,
      "lng": 28.825
    },
    {
      "cityName": "(( Stodolna ))",
      "lat": 47.55,
      "lng": 29.0166667
    },
    {
      "cityName": "Suhuluceni",
      "lat": 47.4663889,
      "lng": 28.5183333
    },
    {
      "cityName": "Susleni",
      "lat": 47.4111111,
      "lng": 28.9863889
    },
    {
      "cityName": "Tabara",
      "lat": 47.33,
      "lng": 28.5647222
    },
    {
      "cityName": "Tantareni",
      "lat": 47.5702778,
      "lng": 28.5625
    },
    {
      "cityName": "Teleseu",
      "lat": 47.2661111,
      "lng": 28.7080556
    },
    {
      "cityName": "Tiganesti",
      "lat": 47.2988889,
      "lng": 28.5522222
    },
    {
      "cityName": "Tipova",
      "lat": 47.605,
      "lng": 28.9794444
    },
    {
      "cityName": "Tîrzieni",
      "lat": 47.445,
      "lng": 28.6236111
    },
    {
      "cityName": "Trebujeni",
      "lat": 47.3138889,
      "lng": 28.9736111
    },
    {
      "cityName": "Trifeshti",
      "lat": 47.6763889,
      "lng": 28.8027778
    },
    {
      "cityName": "Vascauti",
      "lat": 47.4325,
      "lng": 29.0755556
    },
    {
      "cityName": "Vasieni",
      "lat": 47.4608333,
      "lng": 28.4444444
    },
    {
      "cityName": "Vatich",
      "lat": 47.3408333,
      "lng": 28.6219444
    },
    {
      "cityName": "Verejeni",
      "lat": 47.5341667,
      "lng": 28.4705556
    },
    {
      "cityName": "Vîprova",
      "lat": 47.3833333,
      "lng": 28.5705556
    },
    {
      "cityName": "Vorotets",
      "lat": 47.5591667,
      "lng": 28.8547222
    },
    {
      "cityName": "Zagaykani Vek'",
      "lat": 47.5213889,
      "lng": 28.5080556
    },
    {
      "cityName": "Zagoreny",
      "lat": 47.5758333,
      "lng": 28.7275
    },
    {
      "cityName": "Zahareuca",
      "lat": 47.5316667,
      "lng": 28.5994444
    },
    {
      "cityName": "Zazulenii Vechi",
      "lat": 47.6166667,
      "lng": 28.9919444
    },
    {
      "cityName": "Zhurka",
      "lat": 47.4941667,
      "lng": 29.1116667
    },
    {
      "cityName": "Zorile",
      "lat": 47.4566667,
      "lng": 28.7380556
    }
  ]
}